wmc_test_pypi/__init__.py
wmc_test_pypi/__main__.py
wmc_test_pypi/cli.py
wmc_test_pypi-0.0.6.dist-info/LICENSE
wmc_test_pypi-0.0.6.dist-info/METADATA
wmc_test_pypi-0.0.6.dist-info/WHEEL
wmc_test_pypi-0.0.6.dist-info/entry_points.txt
wmc_test_pypi-0.0.6.dist-info/top_level.txt
wmc_test_pypi-0.0.6.dist-info/RECORD
