Metadata-Version: 2.1
Name: wmc-test-pypi
Version: 0.0.6
Summary: wmc test package
Home-page: https://github.com/wmc1992/wmc-test-pypi
Author: wmc1992
Author-email: m18810541081@163.com
License: MIT
Keywords: test pypi
Platform: UNKNOWN
Classifier: Programming Language :: Python :: 3
Classifier: License :: OSI Approved :: MIT License
Classifier: Operating System :: POSIX :: Linux
Requires-Python: >=3.6
Requires-Dist: six (>=1.7)
